inference_providers/__init__.py
inference_providers/inference_providers.json
inference_providers/inference_providers.py
inference_providers-0.2.3.dist-info/LICENSE
inference_providers-0.2.3.dist-info/METADATA
inference_providers-0.2.3.dist-info/WHEEL
inference_providers-0.2.3.dist-info/top_level.txt
inference_providers-0.2.3.dist-info/RECORD
