Metadata-Version: 2.1
Name: inference-providers
Version: 0.2.3
Summary: A collection of commercial LLM inference providers and their available models
Author-email: Stuart Riffle <stuart@rifflemail.com>
Project-URL: Homepage, https://github.com/stuartriffle/inference-providers
Classifier: Programming Language :: Python :: 3
Classifier: License :: OSI Approved :: MIT License
Classifier: Operating System :: OS Independent
Classifier: Development Status :: 4 - Beta
Requires-Python: >=3.8
License-File: LICENSE
